ksfest/__init__.py
ksfest/cli.py
ksfest/ksfest.py
ksfest/utils.py
ksfest-0.1.22.dist-info/AUTHORS.rst
ksfest-0.1.22.dist-info/LICENSE
ksfest-0.1.22.dist-info/METADATA
ksfest-0.1.22.dist-info/WHEEL
ksfest-0.1.22.dist-info/entry_points.txt
ksfest-0.1.22.dist-info/top_level.txt
ksfest-0.1.22.dist-info/RECORD
